ovos_stt_plugin_mms/__init__.py
ovos_stt_plugin_mms/version.py
ovos_stt_plugin_mms-0.2.0.dist-info/LICENSE
ovos_stt_plugin_mms-0.2.0.dist-info/METADATA
ovos_stt_plugin_mms-0.2.0.dist-info/WHEEL
ovos_stt_plugin_mms-0.2.0.dist-info/entry_points.txt
ovos_stt_plugin_mms-0.2.0.dist-info/top_level.txt
ovos_stt_plugin_mms-0.2.0.dist-info/zip-safe
ovos_stt_plugin_mms-0.2.0.dist-info/RECORD
