Metadata-Version: 2.1
Name: ovos-stt-plugin-mms
Version: 0.2.0
Summary: A mms stt plugin for OVOS
Home-page: https://github.com/OpenVoiceOS/ovos-stt-plugin-mms
Author: JarbasAi
Author-email: jarbasai@mailfence.com
License: Apache-2.0
Keywords: ovos plugin stt
Platform: UNKNOWN
Classifier: Development Status :: 3 - Alpha
Classifier: Intended Audience :: Developers
Classifier: Topic :: Text Processing :: Linguistic
Classifier: License :: OSI Approved :: Apache Software License
Classifier: Programming Language :: Python :: 2
Classifier: Programming Language :: Python :: 2.7
Classifier: Programming Language :: Python :: 3
Classifier: Programming Language :: Python :: 3.0
Classifier: Programming Language :: Python :: 3.1
Classifier: Programming Language :: Python :: 3.2
Classifier: Programming Language :: Python :: 3.3
Classifier: Programming Language :: Python :: 3.4
Classifier: Programming Language :: Python :: 3.5
Classifier: Programming Language :: Python :: 3.6
Requires-Dist: ovos-plugin-manager>=0.0.24
Requires-Dist: ovos-utils<1.0.0,>=0.2.1
Requires-Dist: SpeechRecognition~=3.8
Requires-Dist: ovos-stt-plugin-wav2vec<1.0.0,>=0.3.0
